IngeoDash/__init__.py
IngeoDash/__main__.py
IngeoDash/annotate.py
IngeoDash/app.py
IngeoDash/config.py
IngeoDash/download.py
IngeoDash/upload.py
IngeoDash/tests/test_annotate.py
IngeoDash/tests/test_app.py
IngeoDash/tests/test_config.py
IngeoDash/tests/test_download.py
IngeoDash/tests/test_upload.py
IngeoDash-0.1.2.dist-info/LICENSE
IngeoDash-0.1.2.dist-info/METADATA
IngeoDash-0.1.2.dist-info/WHEEL
IngeoDash-0.1.2.dist-info/top_level.txt
IngeoDash-0.1.2.dist-info/RECORD
