Metadata-Version: 2.1
Name: IngeoDash
Version: 0.1.2
Summary: IngeoDash can help to label a dataset
Author-email: Mario Graff <mgraffg@ieee.org>
License: Apache License Version 2.0
Requires-Python: >=3.8
License-File: LICENSE
Requires-Dist: numpy
Requires-Dist: b4msa
Requires-Dist: microtc
Requires-Dist: evomsa
Requires-Dist: dash
Requires-Dist: dash-bootstrap-components
Requires-Dist: scikit-learn
